pep723widget/__init__.py
pep723widget/_version.py
pep723widget/handlers.py
pep723widget/tests/__init__.py
pep723widget/tests/test_handlers.py
pep723widget-0.3.1.data/data/etc/jupyter/jupyter_server_config.d/pep723widget.json
pep723widget-0.3.1.data/data/share/jupyter/labextensions/pep723widget/package.json
pep723widget-0.3.1.data/data/share/jupyter/labextensions/pep723widget/schemas/pep723widget/package.json.orig
pep723widget-0.3.1.data/data/share/jupyter/labextensions/pep723widget/schemas/pep723widget/plugin.json
pep723widget-0.3.1.data/data/share/jupyter/labextensions/pep723widget/static/675.e6bbad1b24eb882b683b.js
pep723widget-0.3.1.data/data/share/jupyter/labextensions/pep723widget/static/728.687ccbf79223394b4ff4.js
pep723widget-0.3.1.data/data/share/jupyter/labextensions/pep723widget/static/remoteEntry.5815da6f71bae13880db.js
pep723widget-0.3.1.data/data/share/jupyter/labextensions/pep723widget/static/style.js
pep723widget-0.3.1.data/data/share/jupyter/labextensions/pep723widget/static/third-party-licenses.json
pep723widget-0.3.1.data/data/share/jupyter/labextensions/pep723widget/install.json
pep723widget-0.3.1.dist-info/METADATA
pep723widget-0.3.1.dist-info/WHEEL
pep723widget-0.3.1.dist-info/licenses/LICENSE
pep723widget-0.3.1.dist-info/RECORD
